Metadata-Version: 1.1
Name: pdfebc-core
Version: 0.3.0
Summary: Core functions of the pdfebc tools. The pdfebc tools is (going to be) a .set of tools for compressing PDF files to e-reader friendly sizes.
Home-page: https://github.com/slarse/pdfebc-core
Author: Simon Larsén
Author-email: slarse@kth.se
License: MIT License
